LICENSE
README.md
pyproject.toml
setup.py
psb2/__init__.py
psb2/format.py
psb2/psb2.py
psb2.egg-info/PKG-INFO
psb2.egg-info/SOURCES.txt
psb2.egg-info/dependency_links.txt
psb2.egg-info/requires.txt
psb2.egg-info/top_level.txt