Metadata-Version: 2.4
Name: psb2
Version: 1.1.2
Summary: Utilities for sampling the datasets of PSB2.
Home-page: https://github.com/thelmuth/psb2-python
Author: Thomas Helmuth and contributors
Author-email: thelmuth@hamilton.edu
License: Eclipse Public License 2.0 (EPL-2.0)
Project-URL: More information, https://cs.hamilton.edu/~thelmuth/PSB2/PSB2.html
Project-URL: Dataset archive, https://zenodo.org/record/4678739
Classifier: Programming Language :: Python :: 3
Classifier: Intended Audience :: Developers
Classifier: Intended Audience :: Information Technology
Classifier: Intended Audience :: Science/Research
Classifier: License :: OSI Approved :: Eclipse Public License 2.0 (EPL-2.0)
License-File: LICENSE
Requires-Dist: requests
Dynamic: author
Dynamic: author-email
Dynamic: classifier
Dynamic: description
Dynamic: description-content-type
Dynamic: home-page
Dynamic: license
Dynamic: license-file
Dynamic: project-url
Dynamic: requires-dist
Dynamic: summary
